my_trino_lib/__init__.py
my_trino_lib/connection.py
my_trino_lib/queries.py
tests/__init__.py
tests/test_connection.py
my_trino_lib-0.1.0.dist-info/METADATA
my_trino_lib-0.1.0.dist-info/WHEEL
my_trino_lib-0.1.0.dist-info/top_level.txt
my_trino_lib-0.1.0.dist-info/RECORD
