Metadata-Version: 2.1
Name: my-trino-lib
Version: 0.1.0
Summary: A library for connecting to Trino and performing SQL operations.
Home-page: https://github.com/yourusername/my_trino_lib
Author: Your Name
Author-email: your.email@example.com
License: UNKNOWN
Platform: UNKNOWN
Classifier: Programming Language :: Python :: 3
Classifier: License :: OSI Approved :: MIT License
Classifier: Operating System :: OS Independent
Requires-Python: >=3.6
Requires-Dist: sqlalchemy
Requires-Dist: trino
